gordon/__init__.py
gordon/exceptions.py
gordon/interfaces.py
gordon/main.py
gordon/plugins_loader.py
gordon/record_checker.py
gordon/router.py
gordon/metrics/__init__.py
gordon/metrics/ffwd.py
gordon/metrics/log.py
tests/__init__.py
tests/unit/__init__.py
tests/unit/conftest.py
tests/unit/test_main.py
tests/unit/test_plugins_loader.py
tests/unit/test_record_checker.py
tests/unit/test_router.py
gordon_dns-0.0.1.dev10.dist-info/LICENSE
gordon_dns-0.0.1.dev10.dist-info/METADATA
gordon_dns-0.0.1.dev10.dist-info/WHEEL
gordon_dns-0.0.1.dev10.dist-info/entry_points.txt
gordon_dns-0.0.1.dev10.dist-info/top_level.txt
gordon_dns-0.0.1.dev10.dist-info/RECORD
